AUTHORS
LICENSE
MANIFEST.in
README.md
setup.py
dbpool/__init__.py
dbpool/db/__init__.py
dbpool/db/backends/__init__.py
dbpool/db/backends/postgis/__init__.py
dbpool/db/backends/postgis/base.py
dbpool/db/backends/postgresql_psycopg2/__init__.py
dbpool/db/backends/postgresql_psycopg2/base.py
django_db_pool.egg-info/PKG-INFO
django_db_pool.egg-info/SOURCES.txt
django_db_pool.egg-info/dependency_links.txt
django_db_pool.egg-info/not-zip-safe
django_db_pool.egg-info/requires.txt
django_db_pool.egg-info/top_level.txt