Metadata-Version: 1.0
Name: django-db-pool
Version: 0.0.10
Summary: Basic database persistance / connection pooling for Django + Postgres.
Home-page: https://github.com/gmcguire/django-db-pool
Author: Greg McGuire
Author-email: gregjmcguire+github@gmail.com
License: BSD licence, see LICENSE
Platform: UNKNOWN
Classifier: Topic :: Database
Classifier: Development Status :: 3 - Alpha
Classifier: Environment :: Web Environment
Classifier: Framework :: Django
Classifier: Intended Audience :: Developers
Classifier: License :: OSI Approved :: BSD License
Classifier: Natural Language :: English
Classifier: Programming Language :: Python
